hack4u/__init__.py
hack4u/courses.py
hack4u/utils.py
academia_hack4u-0.5.1.dist-info/METADATA
academia_hack4u-0.5.1.dist-info/WHEEL
academia_hack4u-0.5.1.dist-info/top_level.txt
academia_hack4u-0.5.1.dist-info/RECORD
