Metadata-Version: 2.4
Name: academia_hack4u
Version: 0.5.1
Summary: Una biblioteca para consultar cursos de hack4u.
Home-page: https://hack4u.io
Author: Iván Jiménez
Dynamic: author
Dynamic: description
Dynamic: description-content-type
Dynamic: home-page
Dynamic: summary
